overtokenizer.py
overtokenizer-0.1.0.dist-info/DESCRIPTION.rst
overtokenizer-0.1.0.dist-info/METADATA
overtokenizer-0.1.0.dist-info/RECORD
overtokenizer-0.1.0.dist-info/WHEEL
overtokenizer-0.1.0.dist-info/entry_points.txt
overtokenizer-0.1.0.dist-info/metadata.json
overtokenizer-0.1.0.dist-info/top_level.txt
