Metadata-Version: 2.0
Name: overtokenizer
Version: 0.1.0
Summary: Unicode-based language-agnostic (over-) tokenizer.
Home-page: https://bitbucket.org/luismsgomes/overtokenizer
Author: Luís Gomes
Author-email: luismsgomes@gmail.com
License: LGPLv2
Keywords: text tokenization pre-processing
Platform: UNKNOWN
Classifier: Development Status :: 4 - Beta
Classifier: Intended Audience :: Developers
Classifier: Topic :: Text Processing :: Linguistic
Classifier: License :: OSI Approved :: GNU Lesser General Public License v2 or later (LGPLv2+)
Classifier: Programming Language :: Python :: 3.5
Requires-Dist: docopt
Requires-Dist: openfile
Requires-Dist: regex
